{
    "ba9b0c86-c51b-0a36-3f7f-80311f73bda1": {
        "paletteKey": "FlexLayoutCol",
        "commentid": null,
        "designerReference": [
            {
                "_key": "componentLabel",
                "_value": "Column",
                "_type": "kv",
                "_attrDef": "p",
                "_useAsLabel": true
            },
            {
                "_key": "style",
                "_value": "",
                "_type": "kv",
                "_attrDef": "p"
            },
            {
                "_key": "class",
                "_value": "",
                "_type": "dav",
                "_attrDef": "p"
            },
            {
                "_key": "fxFlex",
                "_value": "",
                "_type": "kv",
                "_attrDef": "p"
            },
            {
                "_key": "fxLayoutGap",
                "_value": "",
                "_type": "kv",
                "_attrDef": "p"
            },
            {
                "_key": "wrap",
                "_value": "wrap",
                "_type": "a",
                "_attrDef": "p"
            },
            {
                "_key": "layoutAlign",
                "_value": "start",
                "_type": "a",
                "_attrDef": "p"
            },
            {
                "_key": "pLayoutAlign",
                "_value": "stretch",
                "_type": "a",
                "_attrDef": "p"
            },
            {
                "_key": "[fxShow]",
                "_value": "true",
                "_type": "kv",
                "_attrDef": "p"
            }
        ],
        "3720916c-7d53-278e-f87c-4701c662d9d0": {
            "paletteKey": "FlexLayoutRow",
            "parentEditorKey": "ba9b0c86-c51b-0a36-3f7f-80311f73bda1",
            "commentid": null,
            "designerReference": [
                {
                    "_key": "componentLabel",
                    "_value": "Row",
                    "_type": "kv",
                    "_attrDef": "p",
                    "_useAsLabel": true
                },
                {
                    "_key": "style",
                    "_value": "",
                    "_type": "kv",
                    "_attrDef": "p"
                },
                {
                    "_key": "class",
                    "_value": [
                        "cursor-pointer"
                    ],
                    "_type": "dav",
                    "_attrDef": "p"
                },
                {
                    "_key": "fxFlex",
                    "_value": "",
                    "_type": "kv",
                    "_attrDef": "p"
                },
                {
                    "_key": "fxLayoutGap",
                    "_value": "10px",
                    "_type": "kv",
                    "_attrDef": "p"
                },
                {
                    "_key": "wrap",
                    "_value": "wrap",
                    "_type": "a",
                    "_attrDef": "p"
                },
                {
                    "_key": "layoutAlign",
                    "_value": "start",
                    "_type": "a",
                    "_attrDef": "p"
                },
                {
                    "_key": "pLayoutAlign",
                    "_value": "none",
                    "_type": "a",
                    "_attrDef": "p"
                },
                {
                    "_key": "[fxShow]",
                    "_value": "true",
                    "_type": "kv",
                    "_attrDef": "p"
                },
                {
                    "_key": "[matMenuTriggerFor]",
                    "_value": "menu",
                    "_type": "kv",
                    "_attrDef": "c"
                }
            ],
            "50e855bd-702a-bd4f-eeae-f2cb69bb0d8b": {
                "paletteKey": "FlexLayoutCol",
                "parentEditorKey": "3720916c-7d53-278e-f87c-4701c662d9d0",
                "commentid": null,
                "designerReference": [
                    {
                        "_key": "componentLabel",
                        "_value": "Column",
                        "_type": "kv",
                        "_attrDef": "p",
                        "_useAsLabel": true
                    },
                    {
                        "_key": "style",
                        "_value": "",
                        "_type": "kv",
                        "_attrDef": "p"
                    },
                    {
                        "_key": "class",
                        "_value": [
                            "user-name"
                        ],
                        "_type": "dav",
                        "_attrDef": "p"
                    },
                    {
                        "_key": "fxFlex",
                        "_value": "",
                        "_type": "kv",
                        "_attrDef": "p"
                    },
                    {
                        "_key": "fxLayoutGap",
                        "_value": "",
                        "_type": "kv",
                        "_attrDef": "p"
                    },
                    {
                        "_key": "wrap",
                        "_value": "wrap",
                        "_type": "a",
                        "_attrDef": "p"
                    },
                    {
                        "_key": "layoutAlign",
                        "_value": "start",
                        "_type": "a",
                        "_attrDef": "p"
                    },
                    {
                        "_key": "pLayoutAlign",
                        "_value": "stretch",
                        "_type": "a",
                        "_attrDef": "p"
                    },
                    {
                        "_key": "[fxShow]",
                        "_value": "true",
                        "_type": "kv",
                        "_attrDef": "p"
                    },
                    {
                        "_key": "*ngIf",
                        "_value": "page.loaded",
                        "_type": "kv",
                        "_attrDef": "c"
                    }
                ],
                "5bad18f2-0efc-a7f0-cdf4-8392e8ccda96": {
                    "paletteKey": "Html5",
                    "parentEditorKey": "50e855bd-702a-bd4f-eeae-f2cb69bb0d8b",
                    "isAdvancedComponent": true,
                    "commentid": null,
                    "designerReference": [
                        {
                            "_key": "style",
                            "_value": "",
                            "_type": "kv",
                            "_attrDef": "p"
                        },
                        {
                            "_key": "class",
                            "_value": [
                                "initial",
                                "center",
                                "font-12"
                            ],
                            "_type": "dav",
                            "_attrDef": "p"
                        },
                        {
                            "_key": "htmlElement",
                            "_value": "div",
                            "_type": "dav",
                            "_attrDef": "p",
                            "_useAsLabel": true
                        },
                        {
                            "_key": "tagType",
                            "_value": "",
                            "_type": "a",
                            "_attrDef": "p",
                            "_visibility": false
                        },
                        {
                            "_key": "name",
                            "_value": "",
                            "_type": "kv",
                            "_attrDef": "p",
                            "_visibility": false
                        },
                        {
                            "_key": "sandbox",
                            "_value": "",
                            "_type": "kv",
                            "_attrDef": "p",
                            "_visibility": false
                        },
                        {
                            "_key": "src",
                            "_value": "",
                            "_type": "kv",
                            "_attrDef": "p",
                            "_visibility": false
                        },
                        {
                            "_key": "srcdoc",
                            "_value": "",
                            "_type": "kv",
                            "_attrDef": "p",
                            "_visibility": false
                        },
                        {
                            "_key": "width",
                            "_value": "",
                            "_type": "kv",
                            "_attrDef": "p",
                            "_visibility": false
                        },
                        {
                            "_key": "[autoplay]",
                            "_value": "",
                            "_type": "kv",
                            "_attrDef": "p",
                            "_visibility": false
                        },
                        {
                            "_key": "[loop]",
                            "_value": "",
                            "_type": "kv",
                            "_attrDef": "p",
                            "_visibility": false
                        },
                        {
                            "_key": "data",
                            "_value": "",
                            "_type": "kv",
                            "_attrDef": "p",
                            "_visibility": false
                        },
                        {
                            "_key": "audioSource",
                            "_value": [],
                            "_type": "a",
                            "_attrDef": "p",
                            "_visibility": false
                        },
                        {
                            "_key": "videoSource",
                            "_value": [],
                            "_type": "a",
                            "_attrDef": "p",
                            "_visibility": false
                        },
                        {
                            "_key": "audioDatasource",
                            "_value": "",
                            "_type": "a",
                            "_attrDef": "p",
                            "_visibility": false
                        },
                        {
                            "_key": "audioSrc",
                            "_value": "",
                            "_type": "a",
                            "_attrDef": "p",
                            "_visibility": false
                        },
                        {
                            "_key": "audioType",
                            "_value": "",
                            "_type": "a",
                            "_attrDef": "p",
                            "_visibility": false
                        },
                        {
                            "_key": "videoDatasource",
                            "_value": "",
                            "_type": "a",
                            "_attrDef": "p",
                            "_visibility": false
                        },
                        {
                            "_key": "videoSrc",
                            "_value": "",
                            "_type": "a",
                            "_attrDef": "p",
                            "_visibility": false
                        },
                        {
                            "_key": "videoType",
                            "_value": "",
                            "_type": "a",
                            "_attrDef": "p",
                            "_visibility": false
                        },
                        {
                            "_key": "(audioplay)",
                            "_value": "",
                            "_type": "a",
                            "_attrDef": "p",
                            "_visibility": false
                        },
                        {
                            "_key": "(videoplay)",
                            "_value": "",
                            "_type": "a",
                            "_attrDef": "p",
                            "_visibility": false
                        },
                        {
                            "_key": "(audiopause)",
                            "_value": "",
                            "_type": "kv",
                            "_attrDef": "p",
                            "_visibility": false
                        },
                        {
                            "_key": "(videopause)",
                            "_value": "",
                            "_type": "kv",
                            "_attrDef": "p",
                            "_visibility": false
                        },
                        {
                            "_key": "(audioended)",
                            "_value": "",
                            "_type": "kv",
                            "_attrDef": "p",
                            "_visibility": false
                        },
                        {
                            "_key": "(videoended)",
                            "_value": "",
                            "_type": "kv",
                            "_attrDef": "p",
                            "_visibility": false
                        }
                    ],
                    "2c2a812f-4a57-d8c8-d7e3-48c2a211d3c4": {
                        "paletteKey": "html-editor",
                        "parentEditorKey": "5bad18f2-0efc-a7f0-cdf4-8392e8ccda96",
                        "isAdvancedChildComponent": true,
                        "commentid": null,
                        "designerReference": [
                            {
                                "_key": "style",
                                "_value": "",
                                "_type": "kv",
                                "_attrDef": "p"
                            },
                            {
                                "_key": "class",
                                "_value": "",
                                "_type": "dav",
                                "_attrDef": "p"
                            },
                            {
                                "_key": "html",
                                "_value": "{{page.initials | uppercase}}",
                                "_type": "a",
                                "_attrDef": "p"
                            }
                        ]
                    }
                }
            },
            "a2f482eb-4337-9a79-587c-b5bdd67ddf6c": {
                "paletteKey": "FlexLayoutCol",
                "parentEditorKey": "3720916c-7d53-278e-f87c-4701c662d9d0",
                "commentid": null,
                "designerReference": [
                    {
                        "_key": "componentLabel",
                        "_value": "Column",
                        "_type": "kv",
                        "_attrDef": "p",
                        "_useAsLabel": true
                    },
                    {
                        "_key": "style",
                        "_value": "",
                        "_type": "kv",
                        "_attrDef": "p"
                    },
                    {
                        "_key": "class",
                        "_value": [
                            "justify-center"
                        ],
                        "_type": "dav",
                        "_attrDef": "p"
                    },
                    {
                        "_key": "fxFlex",
                        "_value": "",
                        "_type": "kv",
                        "_attrDef": "p"
                    },
                    {
                        "_key": "fxLayoutGap",
                        "_value": "",
                        "_type": "kv",
                        "_attrDef": "p"
                    },
                    {
                        "_key": "wrap",
                        "_value": "wrap",
                        "_type": "a",
                        "_attrDef": "p"
                    },
                    {
                        "_key": "layoutAlign",
                        "_value": "start",
                        "_type": "a",
                        "_attrDef": "p"
                    },
                    {
                        "_key": "pLayoutAlign",
                        "_value": "stretch",
                        "_type": "a",
                        "_attrDef": "p"
                    },
                    {
                        "_key": "[fxShow]",
                        "_value": "true",
                        "_type": "kv",
                        "_attrDef": "p"
                    }
                ],
                "e3c88971-6dcf-aa18-ad0b-23948aecf8eb": {
                    "paletteKey": "Html5",
                    "parentEditorKey": "a2f482eb-4337-9a79-587c-b5bdd67ddf6c",
                    "isAdvancedComponent": true,
                    "commentid": null,
                    "designerReference": [
                        {
                            "_key": "style",
                            "_value": "",
                            "_type": "kv",
                            "_attrDef": "p"
                        },
                        {
                            "_key": "class",
                            "_value": [
                                "font-10"
                            ],
                            "_type": "dav",
                            "_attrDef": "p"
                        },
                        {
                            "_key": "htmlElement",
                            "_value": "div",
                            "_type": "dav",
                            "_attrDef": "p",
                            "_useAsLabel": true
                        },
                        {
                            "_key": "tagType",
                            "_value": "",
                            "_type": "a",
                            "_attrDef": "p",
                            "_visibility": false
                        },
                        {
                            "_key": "name",
                            "_value": "",
                            "_type": "kv",
                            "_attrDef": "p",
                            "_visibility": false
                        },
                        {
                            "_key": "sandbox",
                            "_value": "",
                            "_type": "kv",
                            "_attrDef": "p",
                            "_visibility": false
                        },
                        {
                            "_key": "src",
                            "_value": "",
                            "_type": "kv",
                            "_attrDef": "p",
                            "_visibility": false
                        },
                        {
                            "_key": "srcdoc",
                            "_value": "",
                            "_type": "kv",
                            "_attrDef": "p",
                            "_visibility": false
                        },
                        {
                            "_key": "width",
                            "_value": "",
                            "_type": "kv",
                            "_attrDef": "p",
                            "_visibility": false
                        },
                        {
                            "_key": "[autoplay]",
                            "_value": "",
                            "_type": "kv",
                            "_attrDef": "p",
                            "_visibility": false
                        },
                        {
                            "_key": "[loop]",
                            "_value": "",
                            "_type": "kv",
                            "_attrDef": "p",
                            "_visibility": false
                        },
                        {
                            "_key": "data",
                            "_value": "",
                            "_type": "kv",
                            "_attrDef": "p",
                            "_visibility": false
                        },
                        {
                            "_key": "audioSource",
                            "_value": [],
                            "_type": "a",
                            "_attrDef": "p",
                            "_visibility": false
                        },
                        {
                            "_key": "videoSource",
                            "_value": [],
                            "_type": "a",
                            "_attrDef": "p",
                            "_visibility": false
                        },
                        {
                            "_key": "audioDatasource",
                            "_value": "",
                            "_type": "a",
                            "_attrDef": "p",
                            "_visibility": false
                        },
                        {
                            "_key": "audioSrc",
                            "_value": "",
                            "_type": "a",
                            "_attrDef": "p",
                            "_visibility": false
                        },
                        {
                            "_key": "audioType",
                            "_value": "",
                            "_type": "a",
                            "_attrDef": "p",
                            "_visibility": false
                        },
                        {
                            "_key": "videoDatasource",
                            "_value": "",
                            "_type": "a",
                            "_attrDef": "p",
                            "_visibility": false
                        },
                        {
                            "_key": "videoSrc",
                            "_value": "",
                            "_type": "a",
                            "_attrDef": "p",
                            "_visibility": false
                        },
                        {
                            "_key": "videoType",
                            "_value": "",
                            "_type": "a",
                            "_attrDef": "p",
                            "_visibility": false
                        },
                        {
                            "_key": "(audioplay)",
                            "_value": "",
                            "_type": "a",
                            "_attrDef": "p",
                            "_visibility": false
                        },
                        {
                            "_key": "(videoplay)",
                            "_value": "",
                            "_type": "a",
                            "_attrDef": "p",
                            "_visibility": false
                        },
                        {
                            "_key": "(audiopause)",
                            "_value": "",
                            "_type": "kv",
                            "_attrDef": "p",
                            "_visibility": false
                        },
                        {
                            "_key": "(videopause)",
                            "_value": "",
                            "_type": "kv",
                            "_attrDef": "p",
                            "_visibility": false
                        },
                        {
                            "_key": "(audioended)",
                            "_value": "",
                            "_type": "kv",
                            "_attrDef": "p",
                            "_visibility": false
                        },
                        {
                            "_key": "(videoended)",
                            "_value": "",
                            "_type": "kv",
                            "_attrDef": "p",
                            "_visibility": false
                        }
                    ],
                    "a5b9e0d8-8b80-d69c-d629-64d5d85dac72": {
                        "paletteKey": "html-editor",
                        "parentEditorKey": "e3c88971-6dcf-aa18-ad0b-23948aecf8eb",
                        "isAdvancedChildComponent": true,
                        "commentid": null,
                        "designerReference": [
                            {
                                "_key": "style",
                                "_value": "",
                                "_type": "kv",
                                "_attrDef": "p"
                            },
                            {
                                "_key": "class",
                                "_value": "",
                                "_type": "dav",
                                "_attrDef": "p"
                            },
                            {
                                "_key": "html",
                                "_value": "{{page.profile_values.designation_name}} <br>",
                                "_type": "a",
                                "_attrDef": "p"
                            }
                        ]
                    }
                },
                "ab1d0ebe-0442-0e71-f0b6-7fa84edc28d6": {
                    "paletteKey": "Html5",
                    "parentEditorKey": "a2f482eb-4337-9a79-587c-b5bdd67ddf6c",
                    "isAdvancedComponent": true,
                    "commentid": null,
                    "designerReference": [
                        {
                            "_key": "style",
                            "_value": "",
                            "_type": "kv",
                            "_attrDef": "p"
                        },
                        {
                            "_key": "class",
                            "_value": [
                                "font-12"
                            ],
                            "_type": "dav",
                            "_attrDef": "p"
                        },
                        {
                            "_key": "htmlElement",
                            "_value": "div",
                            "_type": "dav",
                            "_attrDef": "p",
                            "_useAsLabel": true
                        },
                        {
                            "_key": "tagType",
                            "_value": "",
                            "_type": "a",
                            "_attrDef": "p",
                            "_visibility": false
                        },
                        {
                            "_key": "name",
                            "_value": "",
                            "_type": "kv",
                            "_attrDef": "p",
                            "_visibility": false
                        },
                        {
                            "_key": "sandbox",
                            "_value": "",
                            "_type": "kv",
                            "_attrDef": "p",
                            "_visibility": false
                        },
                        {
                            "_key": "src",
                            "_value": "",
                            "_type": "kv",
                            "_attrDef": "p",
                            "_visibility": false
                        },
                        {
                            "_key": "srcdoc",
                            "_value": "",
                            "_type": "kv",
                            "_attrDef": "p",
                            "_visibility": false
                        },
                        {
                            "_key": "width",
                            "_value": "",
                            "_type": "kv",
                            "_attrDef": "p",
                            "_visibility": false
                        },
                        {
                            "_key": "[autoplay]",
                            "_value": "",
                            "_type": "kv",
                            "_attrDef": "p",
                            "_visibility": false
                        },
                        {
                            "_key": "[loop]",
                            "_value": "",
                            "_type": "kv",
                            "_attrDef": "p",
                            "_visibility": false
                        },
                        {
                            "_key": "data",
                            "_value": "",
                            "_type": "kv",
                            "_attrDef": "p",
                            "_visibility": false
                        },
                        {
                            "_key": "audioSource",
                            "_value": [],
                            "_type": "a",
                            "_attrDef": "p",
                            "_visibility": false
                        },
                        {
                            "_key": "videoSource",
                            "_value": [],
                            "_type": "a",
                            "_attrDef": "p",
                            "_visibility": false
                        },
                        {
                            "_key": "audioDatasource",
                            "_value": "",
                            "_type": "a",
                            "_attrDef": "p",
                            "_visibility": false
                        },
                        {
                            "_key": "audioSrc",
                            "_value": "",
                            "_type": "a",
                            "_attrDef": "p",
                            "_visibility": false
                        },
                        {
                            "_key": "audioType",
                            "_value": "",
                            "_type": "a",
                            "_attrDef": "p",
                            "_visibility": false
                        },
                        {
                            "_key": "videoDatasource",
                            "_value": "",
                            "_type": "a",
                            "_attrDef": "p",
                            "_visibility": false
                        },
                        {
                            "_key": "videoSrc",
                            "_value": "",
                            "_type": "a",
                            "_attrDef": "p",
                            "_visibility": false
                        },
                        {
                            "_key": "videoType",
                            "_value": "",
                            "_type": "a",
                            "_attrDef": "p",
                            "_visibility": false
                        },
                        {
                            "_key": "(audioplay)",
                            "_value": "",
                            "_type": "a",
                            "_attrDef": "p",
                            "_visibility": false
                        },
                        {
                            "_key": "(videoplay)",
                            "_value": "",
                            "_type": "a",
                            "_attrDef": "p",
                            "_visibility": false
                        },
                        {
                            "_key": "(audiopause)",
                            "_value": "",
                            "_type": "kv",
                            "_attrDef": "p",
                            "_visibility": false
                        },
                        {
                            "_key": "(videopause)",
                            "_value": "",
                            "_type": "kv",
                            "_attrDef": "p",
                            "_visibility": false
                        },
                        {
                            "_key": "(audioended)",
                            "_value": "",
                            "_type": "kv",
                            "_attrDef": "p",
                            "_visibility": false
                        },
                        {
                            "_key": "(videoended)",
                            "_value": "",
                            "_type": "kv",
                            "_attrDef": "p",
                            "_visibility": false
                        }
                    ],
                    "70ba2edd-634a-6f78-7b2f-e2dd2721ef6b": {
                        "paletteKey": "html-editor",
                        "parentEditorKey": "ab1d0ebe-0442-0e71-f0b6-7fa84edc28d6",
                        "isAdvancedChildComponent": true,
                        "commentid": null,
                        "designerReference": [
                            {
                                "_key": "style",
                                "_value": "",
                                "_type": "kv",
                                "_attrDef": "p"
                            },
                            {
                                "_key": "class",
                                "_value": "",
                                "_type": "dav",
                                "_attrDef": "p"
                            },
                            {
                                "_key": "html",
                                "_value": "{{page.profile_values.employee_name}}",
                                "_type": "a",
                                "_attrDef": "p"
                            }
                        ]
                    }
                },
                "814c7f4c-16c3-f0c1-281d-cdefa879ed0c": {
                    "paletteKey": "FlexLayoutCol",
                    "parentEditorKey": "a2f482eb-4337-9a79-587c-b5bdd67ddf6c",
                    "commentid": null,
                    "designerReference": [
                        {
                            "_key": "componentLabel",
                            "_value": "Column",
                            "_type": "kv",
                            "_attrDef": "p",
                            "_useAsLabel": true
                        },
                        {
                            "_key": "style",
                            "_value": "",
                            "_type": "kv",
                            "_attrDef": "p"
                        },
                        {
                            "_key": "class",
                            "_value": "",
                            "_type": "dav",
                            "_attrDef": "p"
                        },
                        {
                            "_key": "fxFlex",
                            "_value": "",
                            "_type": "kv",
                            "_attrDef": "p"
                        },
                        {
                            "_key": "fxLayoutGap",
                            "_value": "25px",
                            "_type": "kv",
                            "_attrDef": "p"
                        },
                        {
                            "_key": "wrap",
                            "_value": "wrap",
                            "_type": "a",
                            "_attrDef": "p"
                        },
                        {
                            "_key": "layoutAlign",
                            "_value": "start",
                            "_type": "a",
                            "_attrDef": "p"
                        },
                        {
                            "_key": "pLayoutAlign",
                            "_value": "stretch",
                            "_type": "a",
                            "_attrDef": "p"
                        },
                        {
                            "_key": "[fxShow]",
                            "_value": "true",
                            "_type": "kv",
                            "_attrDef": "p"
                        }
                    ],
                    "a0950381-7cd7-5ed7-b095-e47b185fd4d3": {
                        "paletteKey": "NG-Menu",
                        "parentEditorKey": "814c7f4c-16c3-f0c1-281d-cdefa879ed0c",
                        "commentid": null,
                        "designerReference": [
                            {
                                "_key": "componentLabel",
                                "_value": "Menu",
                                "_type": "kv",
                                "_attrDef": "p",
                                "_useAsLabel": true
                            },
                            {
                                "_key": "class",
                                "_value": [
                                    "bold",
                                    "padding-15",
                                    "menu-panel"
                                ],
                                "_type": "dav",
                                "_attrDef": "p"
                            },
                            {
                                "_key": "xPosition",
                                "_value": "",
                                "_type": "kv",
                                "_attrDef": "p"
                            },
                            {
                                "_key": "yPosition",
                                "_value": "",
                                "_type": "kv",
                                "_attrDef": "p"
                            },
                            {
                                "_key": "matMenu",
                                "_value": "menu",
                                "_type": "vk",
                                "_attrDef": "p"
                            },
                            {
                                "_key": "hasBackdrop",
                                "_value": "",
                                "_type": "kv",
                                "_attrDef": "p"
                            },
                            {
                                "_key": "overlapTrigger",
                                "_value": "",
                                "_type": "kv",
                                "_attrDef": "p"
                            },
                            {
                                "_key": "(closed)",
                                "_value": "",
                                "_type": "kv",
                                "_attrDef": "p"
                            }
                        ],
                        "578bbd40-d630-2287-4122-aa9d2d90340a": {
                            "paletteKey": "FlexLayoutRow",
                            "parentEditorKey": "a0950381-7cd7-5ed7-b095-e47b185fd4d3",
                            "commentid": null,
                            "designerReference": [
                                {
                                    "_key": "componentLabel",
                                    "_value": "Row",
                                    "_type": "kv",
                                    "_attrDef": "p",
                                    "_useAsLabel": true
                                },
                                {
                                    "_key": "style",
                                    "_value": "",
                                    "_type": "kv",
                                    "_attrDef": "p"
                                },
                                {
                                    "_key": "class",
                                    "_value": [
                                        "subMenu",
                                        "cursor-pointer"
                                    ],
                                    "_type": "dav",
                                    "_attrDef": "p"
                                },
                                {
                                    "_key": "fxFlex",
                                    "_value": "",
                                    "_type": "kv",
                                    "_attrDef": "p"
                                },
                                {
                                    "_key": "fxLayoutGap",
                                    "_value": "20px",
                                    "_type": "kv",
                                    "_attrDef": "p"
                                },
                                {
                                    "_key": "wrap",
                                    "_value": "wrap",
                                    "_type": "a",
                                    "_attrDef": "p"
                                },
                                {
                                    "_key": "layoutAlign",
                                    "_value": "start",
                                    "_type": "a",
                                    "_attrDef": "p"
                                },
                                {
                                    "_key": "pLayoutAlign",
                                    "_value": "center",
                                    "_type": "a",
                                    "_attrDef": "p"
                                },
                                {
                                    "_key": "[fxShow]",
                                    "_value": "true",
                                    "_type": "kv",
                                    "_attrDef": "p"
                                },
                                {
                                    "_key": "routerLink",
                                    "_value": "profile",
                                    "_type": "kv",
                                    "_attrDef": "c"
                                }
                            ],
                            "4417f82e-7c05-aa4f-d012-6ec7fd2ed747": {
                                "paletteKey": "NG-icon",
                                "parentEditorKey": "578bbd40-d630-2287-4122-aa9d2d90340a",
                                "commentid": null,
                                "designerReference": [
                                    {
                                        "_key": "style",
                                        "_value": "",
                                        "_type": "kv",
                                        "_attrDef": "p"
                                    },
                                    {
                                        "_key": "class",
                                        "_value": "",
                                        "_type": "dav",
                                        "_attrDef": "p"
                                    },
                                    {
                                        "_key": "IconName",
                                        "_value": "person",
                                        "_type": "a",
                                        "_attrDef": "p",
                                        "_useAsLabel": true
                                    },
                                    {
                                        "_key": "[inline]",
                                        "_value": "",
                                        "_type": "kv",
                                        "_attrDef": "p"
                                    },
                                    {
                                        "_key": "color",
                                        "_value": "",
                                        "_type": "kv",
                                        "_attrDef": "p"
                                    }
                                ]
                            },
                            "a9450558-9c24-e51c-2922-094c8b3ddd47": {
                                "paletteKey": "Html5",
                                "parentEditorKey": "578bbd40-d630-2287-4122-aa9d2d90340a",
                                "isAdvancedComponent": true,
                                "commentid": null,
                                "designerReference": [
                                    {
                                        "_key": "style",
                                        "_value": "",
                                        "_type": "kv",
                                        "_attrDef": "p"
                                    },
                                    {
                                        "_key": "class",
                                        "_value": "",
                                        "_type": "dav",
                                        "_attrDef": "p"
                                    },
                                    {
                                        "_key": "htmlElement",
                                        "_value": "div",
                                        "_type": "dav",
                                        "_attrDef": "p",
                                        "_useAsLabel": true
                                    },
                                    {
                                        "_key": "tagType",
                                        "_value": "",
                                        "_type": "a",
                                        "_attrDef": "p",
                                        "_visibility": false
                                    },
                                    {
                                        "_key": "name",
                                        "_value": "",
                                        "_type": "kv",
                                        "_attrDef": "p",
                                        "_visibility": false
                                    },
                                    {
                                        "_key": "sandbox",
                                        "_value": "",
                                        "_type": "kv",
                                        "_attrDef": "p",
                                        "_visibility": false
                                    },
                                    {
                                        "_key": "src",
                                        "_value": "",
                                        "_type": "kv",
                                        "_attrDef": "p",
                                        "_visibility": false
                                    },
                                    {
                                        "_key": "srcdoc",
                                        "_value": "",
                                        "_type": "kv",
                                        "_attrDef": "p",
                                        "_visibility": false
                                    },
                                    {
                                        "_key": "width",
                                        "_value": "",
                                        "_type": "kv",
                                        "_attrDef": "p",
                                        "_visibility": false
                                    },
                                    {
                                        "_key": "[autoplay]",
                                        "_value": "",
                                        "_type": "kv",
                                        "_attrDef": "p",
                                        "_visibility": false
                                    },
                                    {
                                        "_key": "[loop]",
                                        "_value": "",
                                        "_type": "kv",
                                        "_attrDef": "p",
                                        "_visibility": false
                                    },
                                    {
                                        "_key": "data",
                                        "_value": "",
                                        "_type": "kv",
                                        "_attrDef": "p",
                                        "_visibility": false
                                    },
                                    {
                                        "_key": "audioSource",
                                        "_value": [],
                                        "_type": "a",
                                        "_attrDef": "p",
                                        "_visibility": false
                                    },
                                    {
                                        "_key": "videoSource",
                                        "_value": [],
                                        "_type": "a",
                                        "_attrDef": "p",
                                        "_visibility": false
                                    },
                                    {
                                        "_key": "audioDatasource",
                                        "_value": "",
                                        "_type": "a",
                                        "_attrDef": "p",
                                        "_visibility": false
                                    },
                                    {
                                        "_key": "audioSrc",
                                        "_value": "",
                                        "_type": "a",
                                        "_attrDef": "p",
                                        "_visibility": false
                                    },
                                    {
                                        "_key": "audioType",
                                        "_value": "",
                                        "_type": "a",
                                        "_attrDef": "p",
                                        "_visibility": false
                                    },
                                    {
                                        "_key": "videoDatasource",
                                        "_value": "",
                                        "_type": "a",
                                        "_attrDef": "p",
                                        "_visibility": false
                                    },
                                    {
                                        "_key": "videoSrc",
                                        "_value": "",
                                        "_type": "a",
                                        "_attrDef": "p",
                                        "_visibility": false
                                    },
                                    {
                                        "_key": "videoType",
                                        "_value": "",
                                        "_type": "a",
                                        "_attrDef": "p",
                                        "_visibility": false
                                    },
                                    {
                                        "_key": "(audioplay)",
                                        "_value": "",
                                        "_type": "a",
                                        "_attrDef": "p",
                                        "_visibility": false
                                    },
                                    {
                                        "_key": "(videoplay)",
                                        "_value": "",
                                        "_type": "a",
                                        "_attrDef": "p",
                                        "_visibility": false
                                    },
                                    {
                                        "_key": "(audiopause)",
                                        "_value": "",
                                        "_type": "kv",
                                        "_attrDef": "p",
                                        "_visibility": false
                                    },
                                    {
                                        "_key": "(videopause)",
                                        "_value": "",
                                        "_type": "kv",
                                        "_attrDef": "p",
                                        "_visibility": false
                                    },
                                    {
                                        "_key": "(audioended)",
                                        "_value": "",
                                        "_type": "kv",
                                        "_attrDef": "p",
                                        "_visibility": false
                                    },
                                    {
                                        "_key": "(videoended)",
                                        "_value": "",
                                        "_type": "kv",
                                        "_attrDef": "p",
                                        "_visibility": false
                                    }
                                ],
                                "aa484bef-1537-d010-f53d-c635e92b48e8": {
                                    "paletteKey": "html-editor",
                                    "parentEditorKey": "a9450558-9c24-e51c-2922-094c8b3ddd47",
                                    "isAdvancedChildComponent": true,
                                    "commentid": null,
                                    "designerReference": [
                                        {
                                            "_key": "style",
                                            "_value": "",
                                            "_type": "kv",
                                            "_attrDef": "p"
                                        },
                                        {
                                            "_key": "class",
                                            "_value": "",
                                            "_type": "dav",
                                            "_attrDef": "p"
                                        },
                                        {
                                            "_key": "html",
                                            "_value": "Profile",
                                            "_type": "a",
                                            "_attrDef": "p"
                                        }
                                    ]
                                }
                            }
                        },
                        "e4978270-6bec-a878-f516-a48df74773e9": {
                            "paletteKey": "FlexLayoutRow",
                            "parentEditorKey": "a0950381-7cd7-5ed7-b095-e47b185fd4d3",
                            "commentid": null,
                            "designerReference": [
                                {
                                    "_key": "componentLabel",
                                    "_value": "Row",
                                    "_type": "kv",
                                    "_attrDef": "p",
                                    "_useAsLabel": true
                                },
                                {
                                    "_key": "style",
                                    "_value": "",
                                    "_type": "kv",
                                    "_attrDef": "p"
                                },
                                {
                                    "_key": "class",
                                    "_value": [
                                        "subMenu",
                                        "cursor-pointer"
                                    ],
                                    "_type": "dav",
                                    "_attrDef": "p"
                                },
                                {
                                    "_key": "fxFlex",
                                    "_value": "",
                                    "_type": "kv",
                                    "_attrDef": "p"
                                },
                                {
                                    "_key": "fxLayoutGap",
                                    "_value": "20px",
                                    "_type": "kv",
                                    "_attrDef": "p"
                                },
                                {
                                    "_key": "wrap",
                                    "_value": "wrap",
                                    "_type": "a",
                                    "_attrDef": "p"
                                },
                                {
                                    "_key": "layoutAlign",
                                    "_value": "start",
                                    "_type": "a",
                                    "_attrDef": "p"
                                },
                                {
                                    "_key": "pLayoutAlign",
                                    "_value": "center",
                                    "_type": "a",
                                    "_attrDef": "p"
                                },
                                {
                                    "_key": "[fxShow]",
                                    "_value": "true",
                                    "_type": "kv",
                                    "_attrDef": "p"
                                },
                                {
                                    "_key": "(click)",
                                    "_value": "signOut()",
                                    "_type": "kv",
                                    "_attrDef": "c",
                                    "objValue": {
                                        "nodeID": "sd_yj1yaXaxOuKv2bZM",
                                        "functionName": "signOut",
                                        "activeTree": "pages",
                                        "z": "sd_PakUU79XL0j4tv1v",
                                        "input": []
                                    }
                                }
                            ],
                            "f810265c-c44e-44b9-ca75-e8c913676734": {
                                "paletteKey": "NG-icon",
                                "parentEditorKey": "e4978270-6bec-a878-f516-a48df74773e9",
                                "commentid": null,
                                "designerReference": [
                                    {
                                        "_key": "style",
                                        "_value": "",
                                        "_type": "kv",
                                        "_attrDef": "p"
                                    },
                                    {
                                        "_key": "class",
                                        "_value": "",
                                        "_type": "dav",
                                        "_attrDef": "p"
                                    },
                                    {
                                        "_key": "IconName",
                                        "_value": "person",
                                        "_type": "a",
                                        "_attrDef": "p",
                                        "_useAsLabel": true
                                    },
                                    {
                                        "_key": "[inline]",
                                        "_value": "",
                                        "_type": "kv",
                                        "_attrDef": "p"
                                    },
                                    {
                                        "_key": "color",
                                        "_value": "",
                                        "_type": "kv",
                                        "_attrDef": "p"
                                    }
                                ]
                            },
                            "a99091d8-3107-9d78-cb66-0b630c770c36": {
                                "paletteKey": "Html5",
                                "parentEditorKey": "e4978270-6bec-a878-f516-a48df74773e9",
                                "isAdvancedComponent": true,
                                "commentid": null,
                                "designerReference": [
                                    {
                                        "_key": "style",
                                        "_value": "",
                                        "_type": "kv",
                                        "_attrDef": "p"
                                    },
                                    {
                                        "_key": "class",
                                        "_value": "",
                                        "_type": "dav",
                                        "_attrDef": "p"
                                    },
                                    {
                                        "_key": "htmlElement",
                                        "_value": "div",
                                        "_type": "dav",
                                        "_attrDef": "p",
                                        "_useAsLabel": true
                                    },
                                    {
                                        "_key": "tagType",
                                        "_value": "",
                                        "_type": "a",
                                        "_attrDef": "p",
                                        "_visibility": false
                                    },
                                    {
                                        "_key": "name",
                                        "_value": "",
                                        "_type": "kv",
                                        "_attrDef": "p",
                                        "_visibility": false
                                    },
                                    {
                                        "_key": "sandbox",
                                        "_value": "",
                                        "_type": "kv",
                                        "_attrDef": "p",
                                        "_visibility": false
                                    },
                                    {
                                        "_key": "src",
                                        "_value": "",
                                        "_type": "kv",
                                        "_attrDef": "p",
                                        "_visibility": false
                                    },
                                    {
                                        "_key": "srcdoc",
                                        "_value": "",
                                        "_type": "kv",
                                        "_attrDef": "p",
                                        "_visibility": false
                                    },
                                    {
                                        "_key": "width",
                                        "_value": "",
                                        "_type": "kv",
                                        "_attrDef": "p",
                                        "_visibility": false
                                    },
                                    {
                                        "_key": "[autoplay]",
                                        "_value": "",
                                        "_type": "kv",
                                        "_attrDef": "p",
                                        "_visibility": false
                                    },
                                    {
                                        "_key": "[loop]",
                                        "_value": "",
                                        "_type": "kv",
                                        "_attrDef": "p",
                                        "_visibility": false
                                    },
                                    {
                                        "_key": "data",
                                        "_value": "",
                                        "_type": "kv",
                                        "_attrDef": "p",
                                        "_visibility": false
                                    },
                                    {
                                        "_key": "audioSource",
                                        "_value": [],
                                        "_type": "a",
                                        "_attrDef": "p",
                                        "_visibility": false
                                    },
                                    {
                                        "_key": "videoSource",
                                        "_value": [],
                                        "_type": "a",
                                        "_attrDef": "p",
                                        "_visibility": false
                                    },
                                    {
                                        "_key": "audioDatasource",
                                        "_value": "",
                                        "_type": "a",
                                        "_attrDef": "p",
                                        "_visibility": false
                                    },
                                    {
                                        "_key": "audioSrc",
                                        "_value": "",
                                        "_type": "a",
                                        "_attrDef": "p",
                                        "_visibility": false
                                    },
                                    {
                                        "_key": "audioType",
                                        "_value": "",
                                        "_type": "a",
                                        "_attrDef": "p",
                                        "_visibility": false
                                    },
                                    {
                                        "_key": "videoDatasource",
                                        "_value": "",
                                        "_type": "a",
                                        "_attrDef": "p",
                                        "_visibility": false
                                    },
                                    {
                                        "_key": "videoSrc",
                                        "_value": "",
                                        "_type": "a",
                                        "_attrDef": "p",
                                        "_visibility": false
                                    },
                                    {
                                        "_key": "videoType",
                                        "_value": "",
                                        "_type": "a",
                                        "_attrDef": "p",
                                        "_visibility": false
                                    },
                                    {
                                        "_key": "(audioplay)",
                                        "_value": "",
                                        "_type": "a",
                                        "_attrDef": "p",
                                        "_visibility": false
                                    },
                                    {
                                        "_key": "(videoplay)",
                                        "_value": "",
                                        "_type": "a",
                                        "_attrDef": "p",
                                        "_visibility": false
                                    },
                                    {
                                        "_key": "(audiopause)",
                                        "_value": "",
                                        "_type": "kv",
                                        "_attrDef": "p",
                                        "_visibility": false
                                    },
                                    {
                                        "_key": "(videopause)",
                                        "_value": "",
                                        "_type": "kv",
                                        "_attrDef": "p",
                                        "_visibility": false
                                    },
                                    {
                                        "_key": "(audioended)",
                                        "_value": "",
                                        "_type": "kv",
                                        "_attrDef": "p",
                                        "_visibility": false
                                    },
                                    {
                                        "_key": "(videoended)",
                                        "_value": "",
                                        "_type": "kv",
                                        "_attrDef": "p",
                                        "_visibility": false
                                    }
                                ],
                                "f6a8a16a-b074-2734-b0d6-58642f1232b9": {
                                    "paletteKey": "html-editor",
                                    "parentEditorKey": "a99091d8-3107-9d78-cb66-0b630c770c36",
                                    "isAdvancedChildComponent": true,
                                    "commentid": null,
                                    "designerReference": [
                                        {
                                            "_key": "style",
                                            "_value": "",
                                            "_type": "kv",
                                            "_attrDef": "p"
                                        },
                                        {
                                            "_key": "class",
                                            "_value": "",
                                            "_type": "dav",
                                            "_attrDef": "p"
                                        },
                                        {
                                            "_key": "html",
                                            "_value": "Sign out",
                                            "_type": "a",
                                            "_attrDef": "p"
                                        }
                                    ]
                                }
                            }
                        }
                    }
                }
            }
        }
    }
}
